stringzz-0.4.5.dist-info/METADATA
stringzz-0.4.5.dist-info/WHEEL
stringzz-0.4.5.dist-info/licenses/LICENSE
stringzz/__init__.py
stringzz/__init__.pyi
stringzz/py.typed
stringzz/stringzz.cpython-314-x86_64-linux-gnu.so
stringzz-0.4.5.dist-info/RECORD
